odoo/addons/purchase_request_type/README.rst
odoo/addons/purchase_request_type/__init__.py
odoo/addons/purchase_request_type/__manifest__.py
odoo/addons/purchase_request_type/demo/purchase_request_type.xml
odoo/addons/purchase_request_type/i18n/es.po
odoo/addons/purchase_request_type/i18n/it.po
odoo/addons/purchase_request_type/i18n/pt_BR.po
odoo/addons/purchase_request_type/i18n/purchase_request_type.pot
odoo/addons/purchase_request_type/models/__init__.py
odoo/addons/purchase_request_type/models/purchase_request.py
odoo/addons/purchase_request_type/models/purchase_request_type.py
odoo/addons/purchase_request_type/readme/CONFIGURE.md
odoo/addons/purchase_request_type/readme/CONTRIBUTORS.md
odoo/addons/purchase_request_type/readme/DESCRIPTION.md
odoo/addons/purchase_request_type/readme/ROADMAP.md
odoo/addons/purchase_request_type/readme/USAGE.md
odoo/addons/purchase_request_type/security/ir.model.access.csv
odoo/addons/purchase_request_type/security/security.xml
odoo/addons/purchase_request_type/static/description/icon.png
odoo/addons/purchase_request_type/static/description/index.html
odoo/addons/purchase_request_type/tests/__init__.py
odoo/addons/purchase_request_type/tests/test_purchase_request_type.py
odoo/addons/purchase_request_type/views/purchase_request_type_view.xml
odoo/addons/purchase_request_type/views/purchase_request_view.xml
odoo_addon_purchase_request_type-18.0.1.0.0.3.dist-info/METADATA
odoo_addon_purchase_request_type-18.0.1.0.0.3.dist-info/WHEEL
odoo_addon_purchase_request_type-18.0.1.0.0.3.dist-info/top_level.txt
odoo_addon_purchase_request_type-18.0.1.0.0.3.dist-info/RECORD
